{"data": [{"voted_percentage": "22", "won_fight": false, "total_votes": "1359", "fight": "Dodson vs Johnson", "event": "UFC on FOX 6", "tko_vote": "60.135", "sub_vote": "2.365", "dec_vote": "35.811", "tko_outcome": false, "sub_outcome": false, "dec_outcome": false, "draw_outcome": false}, {"voted_percentage": "78", "won_fight": true, "total_votes": "1359", "fight": "Dodson vs Johnson", "event": "UFC on FOX 6", "tko_vote": "4.516", "sub_vote": "3.293", "dec_vote": "90.122", "tko_outcome": false, "sub_outcome": false, "dec_outcome": true, "draw_outcome": false}, {"voted_percentage": "27", "won_fight": false, "total_votes": "1358", "fight": "Jackson vs Teixeira", "event": "UFC on FOX 6", "tko_vote": "78.804", "sub_vote": "1.087", "dec_vote": "17.12", "tko_outcome": false, "sub_outcome": false, "dec_outcome": false, "draw_outcome": false}, {"voted_percentage": "73", "won_fight": true, "total_votes": "1358", "fight": "Jackson vs Teixeira", "event": "UFC on FOX 6", "tko_vote": "48.384", "sub_vote": "16.263", "dec_vote": "33.636", "tko_outcome": false, "sub_outcome": false, "dec_outcome": true, "draw_outcome": false}, {"voted_percentage": "64", "won_fight": true, "total_votes": "1350", "fight": "Pettis vs Cerrone", "event": "UFC on FOX 6", "tko_vote": "24.478", "sub_vote": "5.22", "dec_vote": "68.445", "tko_outcome": true, "sub_outcome": false, "dec_outcome": false, "draw_outcome": false}, {"voted_percentage": "36", "won_fight": false, "total_votes": "1350", "fight": "Pettis vs Cerrone", "event": "UFC on FOX 6", "tko_vote": "15.574", "sub_vote": "8.811", "dec_vote": "72.541", "tko_outcome": false, "sub_outcome": false, "dec_outcome": false, "draw_outcome": false}, {"voted_percentage": "25", "won_fight": true, "total_votes": "1257", "fight": "Lamas vs Koch", "event": "UFC on FOX 6", "tko_vote": "8.777", "sub_vote": "6.583", "dec_vote": "81.818", "tko_outcome": true, "sub_outcome": false, "dec_outcome": false, "draw_outcome": false}, {"voted_percentage": "75", "won_fight": false, "total_votes": "1257", "fight": "Lamas vs Koch", "event": "UFC on FOX 6", "tko_vote": "56.29", "sub_vote": "9.062", "dec_vote": "32.729", "tko_outcome": false, "sub_outcome": false, "dec_outcome": false, "draw_outcome": false}, {"voted_percentage": "63", "won_fight": false, "total_votes": "1236", "fight": "Wiman vs Grant", "event": "UFC on FOX 6", "tko_vote": "7.289", "sub_vote": "13.555", "dec_vote": "76.471", "tko_outcome": false, "sub_outcome": false, "dec_outcome": false, "draw_outcome": false}, {"voted_percentage": "37", "won_fight": true, "total_votes": "1236", "fight": "Wiman vs Grant", "event": "UFC on FOX 6", "tko_vote": "6.608", "sub_vote": "8.37", "dec_vote": "83.7", "tko_outcome": true, "sub_outcome": false, "dec_outcome": false, "draw_outcome": false}, {"voted_percentage": "82", "won_fight": true, "total_votes": "1314", "fight": "Guida vs Hioki", "event": "UFC on FOX 6", "tko_vote": "6.058", "sub_vote": "5.778", "dec_vote": "85.834", "tko_outcome": false, "sub_outcome": false, "dec_outcome": true, "draw_outcome": false}, {"voted_percentage": "18", "won_fight": false, "total_votes": "1314", "fight": "Guida vs Hioki", "event": "UFC on FOX 6", "tko_vote": "4.149", "sub_vote": "39.004", "dec_vote": "56.017", "tko_outcome": false, "sub_outcome": false, "dec_outcome": false, "draw_outcome": false}, {"voted_percentage": "6", "won_fight": false, "total_votes": "1152", "fight": "Stumpf vs Krauss", "event": "UFC on FOX 6", "tko_vote": "15.714", "sub_vote": "21.429", "dec_vote": "57.143", "tko_outcome": false, "sub_outcome": false, "dec_outcome": false, "draw_outcome": false}, {"voted_percentage": "94", "won_fight": true, "total_votes": "1152", "fight": "Stumpf vs Krauss", "event": "UFC on FOX 6", "tko_vote": "12.569", "sub_vote": "23.105", "dec_vote": "61.83", "tko_outcome": false, "sub_outcome": false, "dec_outcome": true, "draw_outcome": false}, {"voted_percentage": "11", "won_fight": false, "total_votes": "1312", "fight": "Matyushenko vs Bader", "event": "UFC on FOX 6", "tko_vote": "79.195", "sub_vote": "4.027", "dec_vote": "14.094", "tko_outcome": false, "sub_outcome": false, "dec_outcome": false, "draw_outcome": false}, {"voted_percentage": "89", "won_fight": true, "total_votes": "1312", "fight": "Matyushenko vs Bader", "event": "UFC on FOX 6", "tko_vote": "70.937", "sub_vote": "3.095", "dec_vote": "23.56", "tko_outcome": false, "sub_outcome": true, "dec_outcome": false, "draw_outcome": false}, {"voted_percentage": "75", "won_fight": false, "total_votes": "1218", "fight": "Russow vs Jordan", "event": "UFC on FOX 6", "tko_vote": "37.541", "sub_vote": "6.529", "dec_vote": "54.189", "tko_outcome": false, "sub_outcome": false, "dec_outcome": false, "draw_outcome": false}, {"voted_percentage": "25", "won_fight": true, "total_votes": "1218", "fight": "Russow vs Jordan", "event": "UFC on FOX 6", "tko_vote": "56.522", "sub_vote": "5.017", "dec_vote": "33.779", "tko_outcome": true, "sub_outcome": false, "dec_outcome": false, "draw_outcome": false}, {"voted_percentage": "88", "won_fight": true, "total_votes": "1048", "fight": "Natal vs Spencer", "event": "UFC on FOX 6", "tko_vote": "3.688", "sub_vote": "51.302", "dec_vote": "43.492", "tko_outcome": false, "sub_outcome": true, "dec_outcome": false, "draw_outcome": false}, {"voted_percentage": "12", "won_fight": false, "total_votes": "1048", "fight": "Natal vs Spencer", "event": "UFC on FOX 6", "tko_vote": "38.889", "sub_vote": "7.143", "dec_vote": "50", "tko_outcome": false, "sub_outcome": false, "dec_outcome": false, "draw_outcome": false}, {"voted_percentage": "87", "won_fight": false, "total_votes": "1127", "fight": "Thoresen vs Mitchell", "event": "UFC on FOX 6", "tko_vote": "8.265", "sub_vote": "42.857", "dec_vote": "46.837", "tko_outcome": false, "sub_outcome": false, "dec_outcome": false, "draw_outcome": false}, {"voted_percentage": "13", "won_fight": true, "total_votes": "1127", "fight": "Thoresen vs Mitchell", "event": "UFC on FOX 6", "tko_vote": "11.565", "sub_vote": "18.367", "dec_vote": "67.347", "tko_outcome": false, "sub_outcome": false, "dec_outcome": true, "draw_outcome": false}]}