{"data": [{"voted_percentage": "52", "won_fight": false, "total_votes": "1826", "fight": "N'Gannou vs Miocic", "event": "UFC 220", "tko_vote": "97.152", "sub_vote": "0.316", "dec_vote": "0.422", "tko_outcome": false, "sub_outcome": false, "dec_outcome": false, "draw_outcome": false}, {"voted_percentage": "48", "won_fight": true, "total_votes": "1826", "fight": "N'Gannou vs Miocic", "event": "UFC 220", "tko_vote": "84.169", "sub_vote": "3.986", "dec_vote": "9.681", "tko_outcome": false, "sub_outcome": false, "dec_outcome": true, "draw_outcome": false}, {"voted_percentage": "20", "won_fight": false, "total_votes": "1829", "fight": "Oezdemir vs Cormier", "event": "UFC 220", "tko_vote": "91.008", "sub_vote": "2.452", "dec_vote": "3.27", "tko_outcome": false, "sub_outcome": false, "dec_outcome": false, "draw_outcome": false}, {"voted_percentage": "80", "won_fight": true, "total_votes": "1829", "fight": "Oezdemir vs Cormier", "event": "UFC 220", "tko_vote": "15.185", "sub_vote": "59.302", "dec_vote": "23.187", "tko_outcome": true, "sub_outcome": false, "dec_outcome": false, "draw_outcome": false}, {"voted_percentage": "84", "won_fight": false, "total_votes": "1709", "fight": "Burgos vs Kattar", "event": "UFC 220", "tko_vote": "16.423", "sub_vote": "2.296", "dec_vote": "78.497", "tko_outcome": false, "sub_outcome": false, "dec_outcome": false, "draw_outcome": false}, {"voted_percentage": "16", "won_fight": true, "total_votes": "1709", "fight": "Burgos vs Kattar", "event": "UFC 220", "tko_vote": "15.809", "sub_vote": "7.721", "dec_vote": "71.324", "tko_outcome": true, "sub_outcome": false, "dec_outcome": false, "draw_outcome": false}, {"voted_percentage": "23", "won_fight": false, "total_votes": "1712", "fight": "Barroso vs Villante", "event": "UFC 220", "tko_vote": "25", "sub_vote": "10.606", "dec_vote": "60.354", "tko_outcome": false, "sub_outcome": false, "dec_outcome": false, "draw_outcome": false}, {"voted_percentage": "77", "won_fight": true, "total_votes": "1712", "fight": "Barroso vs Villante", "event": "UFC 220", "tko_vote": "62.842", "sub_vote": "1.748", "dec_vote": "32.371", "tko_outcome": false, "sub_outcome": false, "dec_outcome": true, "draw_outcome": false}, {"voted_percentage": "13", "won_fight": true, "total_votes": "1751", "fight": "Font vs Almeida", "event": "UFC 220", "tko_vote": "52.991", "sub_vote": "6.838", "dec_vote": "37.179", "tko_outcome": true, "sub_outcome": false, "dec_outcome": false, "draw_outcome": false}, {"voted_percentage": "87", "won_fight": false, "total_votes": "1751", "fight": "Font vs Almeida", "event": "UFC 220", "tko_vote": "70.929", "sub_vote": "5.076", "dec_vote": "21.028", "tko_outcome": false, "sub_outcome": false, "dec_outcome": false, "draw_outcome": false}, {"voted_percentage": "48", "won_fight": true, "total_votes": "1649", "fight": "Bochniak vs Davis", "event": "UFC 220", "tko_vote": "6.053", "sub_vote": "4.666", "dec_vote": "85.75", "tko_outcome": false, "sub_outcome": false, "dec_outcome": true, "draw_outcome": false}, {"voted_percentage": "52", "won_fight": false, "total_votes": "1649", "fight": "Bochniak vs Davis", "event": "UFC 220", "tko_vote": "12.85", "sub_vote": "4.556", "dec_vote": "79.673", "tko_outcome": false, "sub_outcome": false, "dec_outcome": false, "draw_outcome": false}, {"voted_percentage": "87", "won_fight": true, "total_votes": "1665", "fight": "Razak Alhassan vs Homasi", "event": "UFC 220", "tko_vote": "86.565", "sub_vote": "1.524", "dec_vote": "9.211", "tko_outcome": true, "sub_outcome": false, "dec_outcome": false, "draw_outcome": false}, {"voted_percentage": "13", "won_fight": false, "total_votes": "1665", "fight": "Razak Alhassan vs Homasi", "event": "UFC 220", "tko_vote": "56.109", "sub_vote": "4.977", "dec_vote": "32.579", "tko_outcome": false, "sub_outcome": false, "dec_outcome": false, "draw_outcome": false}, {"voted_percentage": "62", "won_fight": false, "total_votes": "1679", "fight": "Pantoja vs Ortiz", "event": "UFC 220", "tko_vote": "6.43", "sub_vote": "30.326", "dec_vote": "59.981", "tko_outcome": false, "sub_outcome": false, "dec_outcome": false, "draw_outcome": false}, {"voted_percentage": "38", "won_fight": true, "total_votes": "1679", "fight": "Pantoja vs Ortiz", "event": "UFC 220", "tko_vote": "8.32", "sub_vote": "7.221", "dec_vote": "80.063", "tko_outcome": false, "sub_outcome": false, "dec_outcome": true, "draw_outcome": false}, {"voted_percentage": "62", "won_fight": false, "total_votes": "1614", "fight": "Ige vs Arce", "event": "UFC 220", "tko_vote": "3.29", "sub_vote": "47.258", "dec_vote": "45.663", "tko_outcome": false, "sub_outcome": false, "dec_outcome": false, "draw_outcome": false}, {"voted_percentage": "38", "won_fight": true, "total_votes": "1614", "fight": "Ige vs Arce", "event": "UFC 220", "tko_vote": "14.894", "sub_vote": "9.493", "dec_vote": "73.322", "tko_outcome": false, "sub_outcome": false, "dec_outcome": true, "draw_outcome": false}, {"voted_percentage": "57", "won_fight": true, "total_votes": "1601", "fight": "Barzola vs Bessette", "event": "UFC 220", "tko_vote": "9.802", "sub_vote": "3.965", "dec_vote": "83.04", "tko_outcome": false, "sub_outcome": false, "dec_outcome": true, "draw_outcome": false}, {"voted_percentage": "43", "won_fight": false, "total_votes": "1601", "fight": "Barzola vs Bessette", "event": "UFC 220", "tko_vote": "20.635", "sub_vote": "11.111", "dec_vote": "64.646", "tko_outcome": false, "sub_outcome": false, "dec_outcome": false, "draw_outcome": false}, {"voted_percentage": "15", "won_fight": false, "total_votes": "1700", "fight": "Tibau vs Makhachev", "event": "UFC 220", "tko_vote": "13.306", "sub_vote": "6.452", "dec_vote": "76.21", "tko_outcome": false, "sub_outcome": false, "dec_outcome": false, "draw_outcome": false}, {"voted_percentage": "85", "won_fight": true, "total_votes": "1700", "fight": "Tibau vs Makhachev", "event": "UFC 220", "tko_vote": "9.711", "sub_vote": "10.193", "dec_vote": "76.997", "tko_outcome": true, "sub_outcome": false, "dec_outcome": false, "draw_outcome": false}]}