{"data": [{"voted_percentage": "24", "won_fight": false, "total_votes": "1858", "fight": "Oleinik vs Overeem", "event": "UFC ON ESPN+ 7", "tko_vote": "16.593", "sub_vote": "76.106", "dec_vote": "3.54", "tko_outcome": false, "sub_outcome": false, "dec_outcome": false, "draw_outcome": false}, {"voted_percentage": "76", "won_fight": true, "total_votes": "1858", "fight": "Oleinik vs Overeem", "event": "UFC ON ESPN+ 7", "tko_vote": "92.319", "sub_vote": "0.782", "dec_vote": "4.267", "tko_outcome": true, "sub_outcome": false, "dec_outcome": false, "draw_outcome": false}, {"voted_percentage": "8", "won_fight": false, "total_votes": "1843", "fight": "Tsarukyan vs Makhachev", "event": "UFC ON ESPN+ 7", "tko_vote": "42.069", "sub_vote": "13.793", "dec_vote": "40.69", "tko_outcome": false, "sub_outcome": false, "dec_outcome": false, "draw_outcome": false}, {"voted_percentage": "92", "won_fight": true, "total_votes": "1843", "fight": "Tsarukyan vs Makhachev", "event": "UFC ON ESPN+ 7", "tko_vote": "10.247", "sub_vote": "26.502", "dec_vote": "59.482", "tko_outcome": false, "sub_outcome": false, "dec_outcome": true, "draw_outcome": false}, {"voted_percentage": "91", "won_fight": true, "total_votes": "1835", "fight": "Pavlovich vs Golm", "event": "UFC ON ESPN+ 7", "tko_vote": "76.284", "sub_vote": "1.016", "dec_vote": "19.056", "tko_outcome": true, "sub_outcome": false, "dec_outcome": false, "draw_outcome": false}, {"voted_percentage": "9", "won_fight": false, "total_votes": "1835", "fight": "Pavlovich vs Golm", "event": "UFC ON ESPN+ 7", "tko_vote": "49.689", "sub_vote": "15.528", "dec_vote": "31.677", "tko_outcome": false, "sub_outcome": false, "dec_outcome": false, "draw_outcome": false}, {"voted_percentage": "11", "won_fight": true, "total_votes": "1866", "fight": "Modafferi vs Shevchenko", "event": "UFC ON ESPN+ 7", "tko_vote": "14.623", "sub_vote": "28.302", "dec_vote": "52.83", "tko_outcome": false, "sub_outcome": false, "dec_outcome": true, "draw_outcome": false}, {"voted_percentage": "89", "won_fight": false, "total_votes": "1866", "fight": "Modafferi vs Shevchenko", "event": "UFC ON ESPN+ 7", "tko_vote": "13.482", "sub_vote": "2.177", "dec_vote": "80.532", "tko_outcome": false, "sub_outcome": false, "dec_outcome": false, "draw_outcome": false}, {"voted_percentage": "55", "won_fight": true, "total_votes": "1793", "fight": "Jotko vs Amedovski", "event": "UFC ON ESPN+ 7", "tko_vote": "19.184", "sub_vote": "6.327", "dec_vote": "71.531", "tko_outcome": false, "sub_outcome": false, "dec_outcome": true, "draw_outcome": false}, {"voted_percentage": "45", "won_fight": false, "total_votes": "1793", "fight": "Jotko vs Amedovski", "event": "UFC ON ESPN+ 7", "tko_vote": "75.646", "sub_vote": "2.583", "dec_vote": "17.589", "tko_outcome": false, "sub_outcome": false, "dec_outcome": false, "draw_outcome": false}, {"voted_percentage": "10", "won_fight": false, "total_votes": "1761", "fight": "Choi vs Evloev", "event": "UFC ON ESPN+ 7", "tko_vote": "46.552", "sub_vote": "9.77", "dec_vote": "39.08", "tko_outcome": false, "sub_outcome": false, "dec_outcome": false, "draw_outcome": false}, {"voted_percentage": "90", "won_fight": true, "total_votes": "1761", "fight": "Choi vs Evloev", "event": "UFC ON ESPN+ 7", "tko_vote": "48.96", "sub_vote": "13.737", "dec_vote": "33.711", "tko_outcome": false, "sub_outcome": false, "dec_outcome": true, "draw_outcome": false}, {"voted_percentage": "44", "won_fight": true, "total_votes": "1752", "fight": "Aliev vs Nakamura", "event": "UFC ON ESPN+ 7", "tko_vote": "15.694", "sub_vote": "3.113", "dec_vote": "77.173", "tko_outcome": false, "sub_outcome": false, "dec_outcome": true, "draw_outcome": false}, {"voted_percentage": "56", "won_fight": false, "total_votes": "1752", "fight": "Aliev vs Nakamura", "event": "UFC ON ESPN+ 7", "tko_vote": "3.976", "sub_vote": "15.596", "dec_vote": "77.574", "tko_outcome": false, "sub_outcome": false, "dec_outcome": false, "draw_outcome": false}, {"voted_percentage": "68", "won_fight": false, "total_votes": "1724", "fight": "da Silva vs Yakovlev", "event": "UFC ON ESPN+ 7", "tko_vote": "53.202", "sub_vote": "20.41", "dec_vote": "23.228", "tko_outcome": false, "sub_outcome": false, "dec_outcome": false, "draw_outcome": false}, {"voted_percentage": "32", "won_fight": true, "total_votes": "1724", "fight": "da Silva vs Yakovlev", "event": "UFC ON ESPN+ 7", "tko_vote": "11.935", "sub_vote": "3.617", "dec_vote": "81.374", "tko_outcome": false, "sub_outcome": true, "dec_outcome": false, "draw_outcome": false}, {"voted_percentage": "79", "won_fight": false, "total_votes": "1799", "fight": "Tybura vs Abdurakhimov", "event": "UFC ON ESPN+ 7", "tko_vote": "18.547", "sub_vote": "3.667", "dec_vote": "74.753", "tko_outcome": false, "sub_outcome": false, "dec_outcome": false, "draw_outcome": false}, {"voted_percentage": "21", "won_fight": true, "total_votes": "1799", "fight": "Tybura vs Abdurakhimov", "event": "UFC ON ESPN+ 7", "tko_vote": "28.609", "sub_vote": "2.887", "dec_vote": "64.042", "tko_outcome": true, "sub_outcome": false, "dec_outcome": false, "draw_outcome": false}, {"voted_percentage": "81", "won_fight": true, "total_votes": "1768", "fight": "Oleksiejczuk vs Antigulov", "event": "UFC ON ESPN+ 7", "tko_vote": "83.078", "sub_vote": "1.393", "dec_vote": "12.535", "tko_outcome": true, "sub_outcome": false, "dec_outcome": false, "draw_outcome": false}, {"voted_percentage": "19", "won_fight": false, "total_votes": "1768", "fight": "Oleksiejczuk vs Antigulov", "event": "UFC ON ESPN+ 7", "tko_vote": "22.289", "sub_vote": "44.578", "dec_vote": "28.916", "tko_outcome": false, "sub_outcome": false, "dec_outcome": false, "draw_outcome": false}, {"voted_percentage": "35", "won_fight": false, "total_votes": "1766", "fight": "Fiziev vs Mustafaev", "event": "UFC ON ESPN+ 7", "tko_vote": "62.46", "sub_vote": "4.045", "dec_vote": "30.097", "tko_outcome": false, "sub_outcome": false, "dec_outcome": false, "draw_outcome": false}, {"voted_percentage": "65", "won_fight": true, "total_votes": "1766", "fight": "Fiziev vs Mustafaev", "event": "UFC ON ESPN+ 7", "tko_vote": "32.23", "sub_vote": "9.495", "dec_vote": "54.878", "tko_outcome": true, "sub_outcome": false, "dec_outcome": false, "draw_outcome": false}]}